compile_songbook/__init__.py
compile_songbook/args.py
compile_songbook/fonts/devpdf/EBB
compile_songbook/fonts/devpdf/EBBI
compile_songbook/fonts/devpdf/EBGaramond-Bold.pfa
compile_songbook/fonts/devpdf/EBGaramond-BoldItalic.pfa
compile_songbook/fonts/devpdf/EBGaramond-Italic.pfa
compile_songbook/fonts/devpdf/EBGaramond-Regular.pfa
compile_songbook/fonts/devpdf/EBI
compile_songbook/fonts/devpdf/EBR
compile_songbook/fonts/devpdf/download
compile_songbook/main.py
compile_songbook/parse.py
compile_songbook/py.typed
compile_songbook/songbook.ms
compile_songbook/songs/а_он_ничей.txt
compile_songbook/songs/а_снег_идёт.txt
compile_songbook/songs/алёша.txt
compile_songbook/songs/ах_мамочка.txt
compile_songbook/songs/белоруссия.txt
compile_songbook/songs/в_лунном_сиянии.txt
compile_songbook/songs/ваше_благородие_госпожа_удача.txt
compile_songbook/songs/верила_верила_верю.txt
compile_songbook/songs/вечерний_звон.txt
compile_songbook/songs/вечный_огонь.txt
compile_songbook/songs/виновата_ли_я.txt
compile_songbook/songs/всё_зависит_от_бога_и_немного_от_нас.txt
compile_songbook/songs/где-то_далеко.txt
compile_songbook/songs/голубой_вагон.txt
compile_songbook/songs/горькая_моя_родина.txt
compile_songbook/songs/государственный_гимн_российской_федерации.txt
compile_songbook/songs/грузинская_песня.txt
compile_songbook/songs/давай_за.txt
compile_songbook/songs/день_победы.txt
compile_songbook/songs/добрый_вечер.txt
compile_songbook/songs/добрый_человек.txt
compile_songbook/songs/дорогой_длинною.txt
compile_songbook/songs/думы_окаянные.txt
compile_songbook/songs/если_б_я_был_султан.txt
compile_songbook/songs/жёны_офицеров.txt
compile_songbook/songs/за_тобою_вслед.txt
compile_songbook/songs/и_кто_его_знает.txt
compile_songbook/songs/казачья_колыбельная_песня.txt
compile_songbook/songs/калинка.txt
compile_songbook/songs/калыханка.txt
compile_songbook/songs/катюша.txt
compile_songbook/songs/когда_весна_придёт_не_знаю.txt
compile_songbook/songs/когда_мои_друзья_со_мной.txt
compile_songbook-0.1.1.dist-info/WHEEL
compile_songbook-0.1.1.dist-info/entry_points.txt
compile_songbook-0.1.1.dist-info/METADATA
compile_songbook-0.1.1.dist-info/RECORD
