Metadata-Version: 2.4
Name: compile-songbook
Version: 0.1.1
Summary: Tool for compiling text files containing lyrics into a single PDF.
Keywords: groff,songs
Author: Ilya Simpson
Author-email: Ilya Simpson <elliot@p-s.co.nz>
License-Expression: AGPL-3.0-or-later
Classifier: Development Status :: 2 - Pre-Alpha
Classifier: Environment :: Console
Classifier: Intended Audience :: Other Audience
Classifier: License :: OSI Approved :: GNU Affero General Public License v3 or later (AGPLv3+)
Classifier: Operating System :: POSIX
Classifier: Programming Language :: Python
Classifier: Programming Language :: Python :: 3.13
Classifier: Topic :: Artistic Software
Classifier: Topic :: Printing
Classifier: Topic :: Text Processing :: Markup
Classifier: Typing :: Typed
Requires-Python: >=3.13
Project-URL: Issues, https://github.com/clockback/songbook/issues
Project-URL: Source, https://github.com/clockback/songbook
